[
  {
    "title": "Aria Chronicle",
    "url": "https://www.aria-chronicle.com/",
    "imgURL": "https://www.aria-chronicle.com/images/product/aria-chronicle.png",
    "ytVideoID": "dV8q6zEDvp8",
    "date": "12 Jul 2020"
  },
  {
    "title": "Parkasaurus",
    "url": "https://www.parkasaurusgame.com",
    "ytVideoID": "1XhTG69PfE4",
    "date": "13 Aug 2020"
  },
  {
    "title": "Littlewood",
    "url": "https://store.steampowered.com/app/894940/Littlewood/",
    "ytVideoID": "_JxrF3QGBT8",
    "date": "4 Aug 2020"
  }
]
